.bumpversion.cfg
.cookiecutterrc
.coveragerc
.editorconfig
.pre-commit-config.yaml
.readthedocs.yml
AUTHORS.rst
CHANGELOG.rst
CONTRIBUTING.rst
LICENSE
MANIFEST.in
README.rst
pyproject.toml
pytest.ini
setup.py
tox.ini
.github/workflows/github-actions.yml
ci/bootstrap.py
ci/requirements.txt
ci/templates/.github/workflows/github-actions.yml
docs/authors.rst
docs/changelog.rst
docs/conf.py
docs/contributing.rst
docs/index.rst
docs/installation.rst
docs/readme.rst
docs/requirements.txt
docs/sg_execution_times.rst
docs/spelling_wordlist.txt
docs/usage.rst
docs/reference/cli.rst
docs/reference/dataset.rst
docs/reference/directory.rst
docs/reference/driver.rst
docs/reference/index.rst
docs/reference/model.rst
examples/README.rst
examples/ground_up_mnist_torch.py
examples/configs/ground_up_mnist_torch_model_config.yml
examples/configs/ground_up_mnist_torch_test_config.yml
examples/configs/ground_up_mnist_torch_train_config.yml
examples/data/interim/.gitkeep
examples/data/processed/.gitkeep
examples/data/raw/.gitkeep
src/kaggle_driver/__init__.py
src/kaggle_driver/__main__.py
src/kaggle_driver/cli.py
src/kaggle_driver/pprint.py
src/kaggle_driver/utils.py
src/kaggle_driver/verbose_print.py
src/kaggle_driver.egg-info/PKG-INFO
src/kaggle_driver.egg-info/SOURCES.txt
src/kaggle_driver.egg-info/dependency_links.txt
src/kaggle_driver.egg-info/entry_points.txt
src/kaggle_driver.egg-info/not-zip-safe
src/kaggle_driver.egg-info/top_level.txt
src/kaggle_driver/dataset/__init__.py
src/kaggle_driver/dataset/data.py
src/kaggle_driver/dataset/data_loc_info.py
src/kaggle_driver/dataset/dataset.py
src/kaggle_driver/dataset/input.py
src/kaggle_driver/dataset/target.py
src/kaggle_driver/dataset/test_data.py
src/kaggle_driver/dataset/train_data.py
src/kaggle_driver/directory/__init__.py
src/kaggle_driver/directory/directory.py
src/kaggle_driver/directory/model_directory.py
src/kaggle_driver/driver/__init__.py
src/kaggle_driver/driver/driver.py
src/kaggle_driver/driver/kaggle_info.py
src/kaggle_driver/model/__init__.py
src/kaggle_driver/model/config.py
src/kaggle_driver/model/model.py
src/kaggle_driver/model/result.py
tests/test_dataset_data_loc_info.py
tests/test_dataset_input.py
tests/test_dataset_target.py
tests/test_directory.py
