Metadata-Version: 2.1
Name: kaggle-driver
Version: 0.0.0
Summary: A package to support model development for Kaggle competitions.
Home-page: https://github.com/christopherpriebe/kaggle-driver
Author: Christopher Priebe
Author-email: christophermpriebe@gmail.com
License: MIT
Project-URL: Documentation, https://kaggle-driver.readthedocs.io/
Project-URL: Changelog, https://kaggle-driver.readthedocs.io/en/latest/changelog.html
Project-URL: Issue Tracker, https://github.com/christopherpriebe/kaggle-driver/issues
Classifier: Development Status :: 5 - Production/Stable
Classifier: Intended Audience :: Developers
Classifier: License :: OSI Approved :: MIT License
Classifier: Operating System :: Unix
Classifier: Operating System :: POSIX
Classifier: Operating System :: Microsoft :: Windows
Classifier: Programming Language :: Python
Classifier: Programming Language :: Python :: 3
Classifier: Programming Language :: Python :: 3 :: Only
Classifier: Programming Language :: Python :: 3.9
Classifier: Programming Language :: Python :: 3.10
Classifier: Programming Language :: Python :: 3.11
Classifier: Programming Language :: Python :: Implementation :: CPython
Classifier: Programming Language :: Python :: Implementation :: PyPy
Classifier: Topic :: Utilities
Requires-Python: >=3.9
License-File: LICENSE
License-File: AUTHORS.rst
